bin_generator/__init__.py
bin_generator/bin_writer.py
bin_generator/config_loader.py
bin_generator/generator.py
bin_generator-0.1.0.data/scripts/bin-generator
bin_generator-0.1.0.dist-info/METADATA
bin_generator-0.1.0.dist-info/WHEEL
bin_generator-0.1.0.dist-info/top_level.txt
bin_generator-0.1.0.dist-info/RECORD
