Metadata-Version: 2.1
Name: bin-generator
Version: 0.1.0
Summary: Conditionally generate small scripts, depending on locally installed programs
Home-page: https://gitlab.com/six-two/bin_generator
Author: six-two
Author-email: pip@six-two.dev
License: MIT License
Classifier: License :: OSI Approved :: MIT License
Classifier: Development Status :: 1 - Planning
Classifier: Operating System :: POSIX :: Linux
Classifier: Programming Language :: Python :: 3
Classifier: Programming Language :: Python :: 3.10
Requires-Python: >=3.8
Requires-Dist: schema (>=0.7.0)
Requires-Dist: PyYAML (>=5.4.0)
Requires-Dist: termcolor (>=1.1.0)
Requires-Dist: munch (>=2.5.0)
Provides-Extra: full
Requires-Dist: Mako (>=1.1.6) ; extra == 'full'
